LICENSE
README.md
pyproject.toml
setup.py
bombadlyanegra/__init__.py
bombadlyanegra/cli.py
bombadlyanegra/main.py
bombadlyanegra/service.py
bombadlyanegra/utils.py
bombadlyanegra.egg-info/PKG-INFO
bombadlyanegra.egg-info/SOURCES.txt
bombadlyanegra.egg-info/dependency_links.txt
bombadlyanegra.egg-info/entry_points.txt
bombadlyanegra.egg-info/requires.txt
bombadlyanegra.egg-info/top_level.txt
bombadlyanegra/app/__init__.py
bombadlyanegra/app/main.py
bombadlyanegra/app/models.py
bombadlyanegra/app/status.py
bombadlyanegra/app/routers/__init__.py
bombadlyanegra/app/routers/attack.py
bombadlyanegra/app/routers/index.py
bombadlyanegra/app/routers/services.py
bombadlyanegra/app/static/css/bootstrap.min.css
bombadlyanegra/app/static/css/bootstrap.min.css.map
bombadlyanegra/app/static/css/index.css
bombadlyanegra/app/static/css/intlTelInput.min.css
bombadlyanegra/app/static/img/flags.png
bombadlyanegra/app/static/img/flags@2x.png
bombadlyanegra/app/static/js/index.js
bombadlyanegra/app/static/js/intlTelInput.min.js
bombadlyanegra/app/static/js/progressbar.min.js
bombadlyanegra/app/static/js/progressbar.min.js.map
bombadlyanegra/app/templates/index.html
bombadlyanegra/services/3040.py
bombadlyanegra/services/585gold.py
bombadlyanegra/services/585zolotoy.py
bombadlyanegra/services/aisttaxi.py
bombadlyanegra/services/alfalife.py
bombadlyanegra/services/alpari.py
bombadlyanegra/services/apteka.py
bombadlyanegra/services/atprime.py
bombadlyanegra/services/av.py
bombadlyanegra/services/avtoobzvon.py
bombadlyanegra/services/bamperby.py
bombadlyanegra/services/bartokyo.py
bombadlyanegra/services/beltelecom.py
bombadlyanegra/services/benzuber.py
bombadlyanegra/services/bluefin.py
bombadlyanegra/services/boosty.py
bombadlyanegra/services/buzzols.py
bombadlyanegra/services/call2friends.py
bombadlyanegra/services/callmyphone.py
bombadlyanegra/services/carsmile.py
bombadlyanegra/services/chefmarket.py
bombadlyanegra/services/cian.py
bombadlyanegra/services/cinema5.py
bombadlyanegra/services/citilink.py
bombadlyanegra/services/city24.py
bombadlyanegra/services/cleversite.py
bombadlyanegra/services/creditter.py
bombadlyanegra/services/crossstudio.py
bombadlyanegra/services/delimobil.py
