Metadata-Version: 2.1
Name: bombadlyanegra
Version: 3.1.4.1
Summary: bomber
Home-page: https://github.com/crinny/bombadlyanegra
Author: skylongg
Author-email: maxxsim.ka007@gmail.com
License: Mozilla Public License 2.0
Platform: UNKNOWN
Classifier: Programming Language :: Python
Classifier: Programming Language :: Python :: 3
Classifier: Programming Language :: Python :: 3.7
Classifier: Operating System :: Android
Classifier: Operating System :: Microsoft :: Windows
Classifier: Topic :: Internet
Classifier: License :: OSI Approved :: Mozilla Public License 2.0 (MPL 2.0)
Requires-Python: >=3.7.0
